wavx/__init__.py
wavx/cli.py
wavx/analysis/__init__.py
wavx/analysis/amplitude.py
wavx/analysis/spectrogram.py
wavx/analysis/waveform.py
wavx/processing/__init__.py
wavx/processing/normalization.py
wavx/tests/__init__.py
wavx/tests/test_amplitude.py
wavx/tests/test_normalization.py
wavx/utils/__init__.py
wavx/utils/logo.py
wavx-0.1.10.dist-info/licenses/LICENSE
wavx-0.1.10.dist-info/METADATA
wavx-0.1.10.dist-info/WHEEL
wavx-0.1.10.dist-info/entry_points.txt
wavx-0.1.10.dist-info/top_level.txt
wavx-0.1.10.dist-info/RECORD
