Metadata-Version: 2.4
Name: wavx
Version: 0.1.10
Summary: 音频分析和处理工具库
Home-page: https://github.com/JiangYain/WavX
Author: Chord
Author-email: chordjiang@gmail.com
Project-URL: Bug Tracker, https://github.com/JiangYain/WavX/issues
Project-URL: Documentation, https://github.com/JiangYain/WavX/tree/main/docs
Project-URL: Source Code, https://github.com/JiangYain/WavX
Classifier: Development Status :: 3 - Alpha
Classifier: Intended Audience :: Developers
Classifier: Intended Audience :: Science/Research
Classifier: License :: OSI Approved :: MIT License
Classifier: Programming Language :: Python :: 3
Classifier: Programming Language :: Python :: 3.10
Classifier: Programming Language :: Python :: 3.11
Classifier: Programming Language :: Python :: 3.12
Classifier: Topic :: Multimedia :: Sound/Audio :: Analysis
Requires-Python: >=3.7
License-File: LICENSE
Requires-Dist: numpy>=1.19.0
Requires-Dist: scipy>=1.5.0
Requires-Dist: matplotlib>=3.3.0
Requires-Dist: soundfile>=0.10.3
Requires-Dist: librosa>=0.8.0
Dynamic: author
Dynamic: author-email
Dynamic: classifier
Dynamic: description
Dynamic: description-content-type
Dynamic: home-page
Dynamic: license-file
Dynamic: project-url
Dynamic: requires-dist
Dynamic: requires-python
Dynamic: summary
